pybase16_builder/__init__.py
pybase16_builder/builder.py
pybase16_builder/cli.py
pybase16_builder/injector.py
pybase16_builder/shared.py
pybase16_builder/updater.py
pybase16_builder-0.2.8.dist-info/LICENSE
pybase16_builder-0.2.8.dist-info/METADATA
pybase16_builder-0.2.8.dist-info/WHEEL
pybase16_builder-0.2.8.dist-info/entry_points.txt
pybase16_builder-0.2.8.dist-info/top_level.txt
pybase16_builder-0.2.8.dist-info/RECORD
