Metadata-Version: 2.1
Name: pybase16-builder
Version: 0.2.8
Summary: A base16 colorscheme builder for Python
Home-page: https://github.com/InspectorMustache/pybase16-builder
Author: Pu Anlai
License: MIT
Keywords: base16
Platform: UNKNOWN
Classifier: Development Status :: 3 - Alpha
Classifier: Intended Audience :: End Users/Desktop
Classifier: Topic :: Other/Nonlisted Topic
Classifier: License :: OSI Approved :: MIT License
Classifier: Programming Language :: Python :: 3.10
Classifier: Programming Language :: Python :: 3 :: Only
Requires-Python: >=3.5
License-File: LICENSE
Requires-Dist: pystache
Requires-Dist: pyyaml
Requires-Dist: aiofiles
